src/26bit_counter/counter.v
module counter(input clk, output [25:0] data);
wire clk;

reg [25:0] data = 0;

//-- Sensitive to rising edge
always @(posedge clk) begin
  data <= data + 1;
end
endmodule

src/26bit_counter/counter_tb.v
module counter_tb();
    
reg clk = 0;
    
wire [25:0] data;

reg [25:0] counter_check = 1;
    
counter C1(
  .clk(clk),
  .data(data)
);
    
always #1 clk = ~clk;
    
always @(negedge clk) begin
  if (counter_check != data)
    $display("-->ERROR!. Expected: %d. Read: %d",counter_check, data);
    
  counter_check <= counter_check + 1;
end
    
initial begin
    
  $dumpfile("counter_tb.vcd");
  $dumpvars(0, counter_tb);
    
  # 0.5 if (data != 0)
          $display("ERROR! Counter is not 0!");
        else
          $display("Counter initialized. OK.");

  # 99 $display("END of simulation");
  # 100 $finish;
 end
 endmodule

src/26bit_counter/counter_tb.vcd
$date
	Tue Jul 21 00:40:39 2020
$end
$version
	Icarus Verilog
$end
$timescale
	1s
$end
$scope module counter_tb $end
$var wire 26 ! data [25:0] $end
$var reg 1 " clk $end
$var reg 26 # counter_check [25:0] $end
$scope module C1 $end
$var wire 1 " clk $end
$var reg 26 $ data [25:0] $end
$upscope $end
$upscope $end
$enddefinitions $end
#0
$dumpvars
b0 $
b1 #
0"
b0 !
$end
#1
b1 !
b1 $
1"
#2
b10 #
0"
#3
b10 !
b10 $
1"
#4
b11 #
0"
#5
b11 !
b11 $
1"
#6
b100 #
0"
#7
b100 !
b100 $
1"
#8
b101 #
0"
#9
b101 !
b101 $
1"
#10
b110 #
0"
#11
b110 !
b110 $
1"
#12
b111 #
0"
#13
b111 !
b111 $
1"
#14
b1000 #
0"
#15
b1000 !
b1000 $
1"
#16
b1001 #
0"
#17
b1001 !
b1001 $
1"
#18
b1010 #
0"
#19
b1010 !
b1010 $
1"
#20
b1011 #
0"
#21
b1011 !
b1011 $
1"
#22
b1100 #
0"
#23
b1100 !
b1100 $
1"
#24
b1101 #
0"
#25
b1101 !
b1101 $
1"
#26
b1110 #
0"
#27
b1110 !
b1110 $
1"
#28
b1111 #
0"
#29
b1111 !
b1111 $
1"
#30
b10000 #
0"
#31
b10000 !
b10000 $
1"
#32
b10001 #
0"
#33
b10001 !
b10001 $
1"
#34
b10010 #
0"
#35
b10010 !
b10010 $
1"
#36
b10011 #
0"
#37
b10011 !
b10011 $
1"
#38
b10100 #
0"
#39
b10100 !
b10100 $
1"
#40
b10101 #
0"
#41
b10101 !
b10101 $
1"
#42
b10110 #
0"
#43
b10110 !
b10110 $
1"
#44
b10111 #
0"
#45
b10111 !
b10111 $
1"
#46
b11000 #
0"
#47
b11000 !
b11000 $
1"
#48
b11001 #
0"
#49
b11001 !
b11001 $
1"
#50
b11010 #
0"
#51
b11010 !
b11010 $
1"
#52
b11011 #
0"
#53
b11011 !
b11011 $
1"
#54
b11100 #
0"
#55
b11100 !
b11100 $
1"
#56
b11101 #
0"
#57
b11101 !
b11101 $
1"
#58
b11110 #
0"
#59
b11110 !
b11110 $
1"
#60
b11111 #
0"
#61
b11111 !
b11111 $
1"
#62
b100000 #
0"
#63
b100000 !
b100000 $
1"
#64
b100001 #
0"
#65
b100001 !
b100001 $
1"
#66
b100010 #
0"
#67
b100010 !
b100010 $
1"
#68
b100011 #
0"
#69
b100011 !
b100011 $
1"
#70
b100100 #
0"
#71
b100100 !
b100100 $
1"
#72
b100101 #
0"
#73
b100101 !
b100101 $
1"
#74
b100110 #
0"
#75
b100110 !
b100110 $
1"
#76
b100111 #
0"
#77
b100111 !
b100111 $
1"
#78
b101000 #
0"
#79
b101000 !
b101000 $
1"
#80
b101001 #
0"
#81
b101001 !
b101001 $
1"
#82
b101010 #
0"
#83
b101010 !
b101010 $
1"
#84
b101011 #
0"
#85
b101011 !
b101011 $
1"
#86
b101100 #
0"
#87
b101100 !
b101100 $
1"
#88
b101101 #
0"
#89
b101101 !
b101101 $
1"
#90
b101110 #
0"
#91
b101110 !
b101110 $
1"
#92
b101111 #
0"
#93
b101111 !
b101111 $
1"
#94
b110000 #
0"
#95
b110000 !
b110000 $
1"
#96
b110001 #
0"
#97
b110001 !
b110001 $
1"
#98
b110010 #
0"
#99
b110010 !
b110010 $
1"
#100
b110011 #
0"
#101
b110011 !
b110011 $
1"
#102
b110100 #
0"
#103
b110100 !
b110100 $
1"
#104
b110101 #
0"
#105
b110101 !
b110101 $
1"
#106
b110110 #
0"
#107
b110110 !
b110110 $
1"
#108
b110111 #
0"
#109
b110111 !
b110111 $
1"
#110
b111000 #
0"
#111
b111000 !
b111000 $
1"
#112
b111001 #
0"
#113
b111001 !
b111001 $
1"
#114
b111010 #
0"
#115
b111010 !
b111010 $
1"
#116
b111011 #
0"
#117
b111011 !
b111011 $
1"
#118
b111100 #
0"
#119
b111100 !
b111100 $
1"
#120
b111101 #
0"
#121
b111101 !
b111101 $
1"
#122
b111110 #
0"
#123
b111110 !
b111110 $
1"
#124
b111111 #
0"
#125
b111111 !
b111111 $
1"
#126
b1000000 #
0"
#127
b1000000 !
b1000000 $
1"
#128
b1000001 #
0"
#129
b1000001 !
b1000001 $
1"
#130
b1000010 #
0"
#131
b1000010 !
b1000010 $
1"
#132
b1000011 #
0"
#133
b1000011 !
b1000011 $
1"
#134
b1000100 #
0"
#135
b1000100 !
b1000100 $
1"
#136
b1000101 #
0"
#137
b1000101 !
b1000101 $
1"
#138
b1000110 #
0"
#139
b1000110 !
b1000110 $
1"
#140
b1000111 #
0"
#141
b1000111 !
b1000111 $
1"
#142
b1001000 #
0"
#143
b1001000 !
b1001000 $
1"
#144
b1001001 #
0"
#145
b1001001 !
b1001001 $
1"
#146
b1001010 #
0"
#147
b1001010 !
b1001010 $
1"
#148
b1001011 #
0"
#149
b1001011 !
b1001011 $
1"
#150
b1001100 #
0"
#151
b1001100 !
b1001100 $
1"
#152
b1001101 #
0"
#153
b1001101 !
b1001101 $
1"
#154
b1001110 #
0"
#155
b1001110 !
b1001110 $
1"
#156
b1001111 #
0"
#157
b1001111 !
b1001111 $
1"
#158
b1010000 #
0"
#159
b1010000 !
b1010000 $
1"
#160
b1010001 #
0"
#161
b1010001 !
b1010001 $
1"
#162
b1010010 #
0"
#163
b1010010 !
b1010010 $
1"
#164
b1010011 #
0"
#165
b1010011 !
b1010011 $
1"
#166
b1010100 #
0"
#167
b1010100 !
b1010100 $
1"
#168
b1010101 #
0"
#169
b1010101 !
b1010101 $
1"
#170
b1010110 #
0"
#171
b1010110 !
b1010110 $
1"
#172
b1010111 #
0"
#173
b1010111 !
b1010111 $
1"
#174
b1011000 #
0"
#175
b1011000 !
b1011000 $
1"
#176
b1011001 #
0"
#177
b1011001 !
b1011001 $
1"
#178
b1011010 #
0"
#179
b1011010 !
b1011010 $
1"
#180
b1011011 #
0"
#181
b1011011 !
b1011011 $
1"
#182
b1011100 #
0"
#183
b1011100 !
b1011100 $
1"
#184
b1011101 #
0"
#185
b1011101 !
b1011101 $
1"
#186
b1011110 #
0"
#187
b1011110 !
b1011110 $
1"
#188
b1011111 #
0"
#189
b1011111 !
b1011111 $
1"
#190
b1100000 #
0"
#191
b1100000 !
b1100000 $
1"
#192
b1100001 #
0"
#193
b1100001 !
b1100001 $
1"
#194
b1100010 #
0"
#195
b1100010 !
b1100010 $
1"
#196
b1100011 #
0"
#197
b1100011 !
b1100011 $
1"
#198
b1100100 #
0"
#199
b1100100 !
b1100100 $
1"
#200
b1100101 #
0"
