src/multiplexor/prescaler.v
module prescaler(input clk_in, output clk_out);

wire clk_in;
wire clk_out;

parameter N = 22;

reg [N-1:0] count = 0;

assign clk_out = count[N-1];

always @(posedge(clk_in)) begin
  count <= count + 1;
end

endmodule

src/multiplexor/mux2.v
module mux2(input wire clk, output reg [3:0] data);

parameter NP = 22;
parameter VAL0 = 4'b1010;
parameter VAL1 = 4'b0101;

wire [3:0] val0;
wire [3:0] val1;
wire sel;

assign val0 = VAL0;
assign val1 = VAL1;

always @(sel or val0 or val1)
  if (sel == 0)
    data <= val0;
  else
    data <= val1;

prescaler #(.N(NP))
  PRES (
    .clk_in(clk),
    .clk_out(sel)
  );

endmodule

src/multiplexor/mux2_tb.v
module mux2_tb();

reg clk = 0;

wire [3:0] data;

mux2 #(.NP(1))
  dut(
    .clk(clk),
    .data(data)
  );

always #1 clk = ~clk;

initial begin
  $dumpfile("mux2_tb.vcd");
  $dumpvars(0, mux2_tb);

  # 30 $display("Start Simulation");
  $finish;
end

endmodule

src/multiplexor/mux2_tb.vcd
$date
	Fri Jul 24 14:59:11 2020
$end
$version
	Icarus Verilog
$end
$timescale
	1s
$end
$scope module mux2_tb $end
$var wire 4 ! data [3:0] $end
$var reg 1 " clk $end
$scope module dut $end
$var wire 1 " clk $end
$var wire 4 # val0 [3:0] $end
$var wire 4 $ val1 [3:0] $end
$var wire 1 % sel $end
$var reg 4 & data [3:0] $end
$scope module PRES $end
$var wire 1 " clk_in $end
$var wire 1 % clk_out $end
$var reg 1 ' count $end
$upscope $end
$upscope $end
$upscope $end
$enddefinitions $end
#0
$dumpvars
0'
b1010 &
0%
b101 $
b1010 #
0"
b1010 !
$end
#1
b101 !
b101 &
1%
1'
1"
#2
0"
#3
b1010 !
b1010 &
0%
0'
1"
#4
0"
#5
b101 !
b101 &
1%
1'
1"
#6
0"
#7
b1010 !
b1010 &
0%
0'
1"
#8
0"
#9
b101 !
b101 &
1%
1'
1"
#10
0"
#11
b1010 !
b1010 &
0%
0'
1"
#12
0"
#13
b101 !
b101 &
1%
1'
1"
#14
0"
#15
b1010 !
b1010 &
0%
0'
1"
#16
0"
#17
b101 !
b101 &
1%
1'
1"
#18
0"
#19
b1010 !
b1010 &
0%
0'
1"
#20
0"
#21
b101 !
b101 &
1%
1'
1"
#22
0"
#23
b1010 !
b1010 &
0%
0'
1"
#24
0"
#25
b101 !
b101 &
1%
1'
1"
#26
0"
#27
b1010 !
b1010 &
0%
0'
1"
#28
0"
#29
b101 !
b101 &
1%
1'
1"
