src/blink/prescaler.v
module prescaler(input clk_in, output clk_out);
wire clk_in;
wire clk_out;

//-- Numero de bits del prescaler (por defecto)
parameter N = 22;

//-- Registro para implementar contador de N bits
reg [N-1:0] count = 0;

//-- El bit más significativo se saca por la salida
assign clk_out = count[N-1];

//-- Contador: se incrementa en flanco de subida
always @(posedge(clk_in)) begin
  count <= count + 1;
end

endmodule

src/shift4/shift4.v
module shift4(input wire clk, output reg [3:0] data);

parameter NP = 21;
parameter INI = 1;

wire clk_pres;

reg load_shift = 0;

wire serin;

prescaler #(.N(NP))
  pres1 (
    .clk_in(clk),
    .clk_out(clk_pres)
  );

// 立ち上がりエッジ時
always @(posedge(clk_pres)) begin
  load_shift <= 1;
end

// 立ち上がりエッジ時
always @(posedge(clk_pres)) begin
  if (load_shift == 0)
    data <= INI;
  else
    data <= {data[2:0], serin};
end

assign serin = data[3];

endmodule

src/shift_register/shift4_tb.v
module shift4_tb();

reg clk = 0;

wire [3:0] data;

shift4 #(.NP(1), .INI(4'b0001))
  C1(
    .clk(clk),
    .data(data)
  );

always #1 clk = ~clk;

initial begin
  $dumpfile("shift4_tb.vcd");
  $dumpvars(0, shift4_tb);

  # 30 $display("Start Simulator");
  $finish;
end

endmodule

src/shift_register/shift4_tb.vcd
$date
	Thu Jul 23 19:45:53 2020
$end
$version
	Icarus Verilog
$end
$timescale
	1s
$end
$scope module shift4_tb $end
$var wire 4 ! data [3:0] $end
$var reg 1 " clk $end
$scope module C1 $end
$var wire 1 " clk $end
$var wire 1 # serin $end
$var wire 1 $ clk_pres $end
$var reg 4 % data [3:0] $end
$var reg 1 & load_shift $end
$scope module pres1 $end
$var wire 1 " clk_in $end
$var wire 1 $ clk_out $end
$var reg 1 ' count $end
$upscope $end
$upscope $end
$upscope $end
$enddefinitions $end
#0
$dumpvars
0'
0&
bx %
0$
x#
0"
bx !
$end
#1
0#
1&
b1 !
b1 %
1$
1'
1"
#2
0"
#3
0$
0'
1"
#4
0"
#5
b10 !
b10 %
1$
1'
1"
#6
0"
#7
0$
0'
1"
#8
0"
#9
b100 !
b100 %
1$
1'
1"
#10
0"
#11
0$
0'
1"
#12
0"
#13
1#
b1000 !
b1000 %
1$
1'
1"
#14
0"
#15
0$
0'
1"
#16
0"
#17
0#
b1 !
b1 %
1$
1'
1"
#18
0"
#19
0$
0'
1"
#20
0"
#21
b10 !
b10 %
1$
1'
1"
#22
0"
#23
0$
0'
1"
#24
0"
#25
b100 !
b100 %
1$
1'
1"
#26
0"
#27
0$
0'
1"
#28
0"
#29
1#
b1000 !
b1000 %
1$
1'
1"
