src/blink/prescaler.v
module prescaler(input clk_in, output clk_out);
wire clk_in;
wire clk_out;

//-- Numero de bits del prescaler (por defecto)
parameter N = 22;

//-- Registro para implementar contador de N bits
reg [N-1:0] count = 0;

//-- El bit más significativo se saca por la salida
assign clk_out = count[N-1];

//-- Contador: se incrementa en flanco de subida
always @(posedge(clk_in)) begin
  count <= count + 1;
end

endmodule

src/blink/blink4.v
//-- blink4.v
module blink4(input wire clk,           //--clock
              output wire [3:0] data);  //-- output register);
    
//-- Bits for the prescaler
parameter N = 22;
    
//-- main clock (prescalor)
wire clk_base;
    
//-- register data
reg [3:0] dout = 0;
    
//-- wire to the register
wire [3:0] din;
    
//-- Instance of the prescaler
prescaler #(.N(N))
  PRES (
    .clk_in(clk),
    .clk_out(clk_base)
  );
    
//-- Register
always @(posedge(clk_base))
  dout <= din;
    
//-- Not gate sets the input to the output
assign din = ~dout;
    
//-- output data from the register to the output of the module
assign data = dout;
    
endmodule

src/blink/blink4_tb.v
//-- blink4.v
module blink4_tb();
    
//-- register to generate the clock signal
reg clk = 0;
    
//-- output data of the component
wire [3:0] data;
    
//-- Instantiate the component
blink4 #(.N(1))
  TOP (
    .clk(clk),
    .data(data)
  );
    
//-- generate the clock with a 2 period cycle
always #1 clk = ~clk;
    
//-- process to start
initial begin
    
  //-- file to store the results 
  $dumpfile("blink4_tb.vcd");
  $dumpvars(0, blink4_tb);
    
  # 100 $display("FIN de la simulacion");
  $finish;     
end
endmodule

src/blink/blink4_tb.vcd
$date
	Sun Jul 19 18:09:33 2020
$end
$version
	Icarus Verilog
$end
$timescale
	1s
$end
$scope module blink4_tb $end
$var wire 4 ! data [3:0] $end
$var reg 1 " clk $end
$scope module TOP $end
$var wire 1 " clk $end
$var wire 4 # data [3:0] $end
$var wire 4 $ din [3:0] $end
$var wire 1 % clk_base $end
$var reg 4 & dout [3:0] $end
$scope module PRES $end
$var wire 1 " clk_in $end
$var wire 1 % clk_out $end
$var reg 1 ' count $end
$upscope $end
$upscope $end
$upscope $end
$enddefinitions $end
#0
$dumpvars
0'
b0 &
0%
b1111 $
b0 #
0"
b0 !
$end
#1
b0 $
b1111 !
b1111 #
b1111 &
1%
1'
1"
#2
0"
#3
0%
0'
1"
#4
0"
#5
b1111 $
b0 !
b0 #
b0 &
1%
1'
1"
#6
0"
#7
0%
0'
1"
#8
0"
#9
b0 $
b1111 !
b1111 #
b1111 &
1%
1'
1"
#10
0"
#11
0%
0'
1"
#12
0"
#13
b1111 $
b0 !
b0 #
b0 &
1%
1'
1"
#14
0"
#15
0%
0'
1"
#16
0"
#17
b0 $
b1111 !
b1111 #
b1111 &
1%
1'
1"
#18
0"
#19
0%
0'
1"
#20
0"
#21
b1111 $
b0 !
b0 #
b0 &
1%
1'
1"
#22
0"
#23
0%
0'
1"
#24
0"
#25
b0 $
b1111 !
b1111 #
b1111 &
1%
1'
1"
#26
0"
#27
0%
0'
1"
#28
0"
#29
b1111 $
b0 !
b0 #
b0 &
1%
1'
1"
#30
0"
#31
0%
0'
1"
#32
0"
#33
b0 $
b1111 !
b1111 #
b1111 &
1%
1'
1"
#34
0"
#35
0%
0'
1"
#36
0"
#37
b1111 $
b0 !
b0 #
b0 &
1%
1'
1"
#38
0"
#39
0%
0'
1"
#40
0"
#41
b0 $
b1111 !
b1111 #
b1111 &
1%
1'
1"
#42
0"
#43
0%
0'
1"
#44
0"
#45
b1111 $
b0 !
b0 #
b0 &
1%
1'
1"
#46
0"
#47
0%
0'
1"
#48
0"
#49
b0 $
b1111 !
b1111 #
b1111 &
1%
1'
1"
#50
0"
#51
0%
0'
1"
#52
0"
#53
b1111 $
b0 !
b0 #
b0 &
1%
1'
1"
#54
0"
#55
0%
0'
1"
#56
0"
#57
b0 $
b1111 !
b1111 #
b1111 &
1%
1'
1"
#58
0"
#59
0%
0'
1"
#60
0"
#61
b1111 $
b0 !
b0 #
b0 &
1%
1'
1"
#62
0"
#63
0%
0'
1"
#64
0"
#65
b0 $
b1111 !
b1111 #
b1111 &
1%
1'
1"
#66
0"
#67
0%
0'
1"
#68
0"
#69
b1111 $
b0 !
b0 #
b0 &
1%
1'
1"
#70
0"
#71
0%
0'
1"
#72
0"
#73
b0 $
b1111 !
b1111 #
b1111 &
1%
1'
1"
#74
0"
#75
0%
0'
1"
#76
0"
#77
b1111 $
b0 !
b0 #
b0 &
1%
1'
1"
#78
0"
#79
0%
0'
1"
#80
0"
#81
b0 $
b1111 !
b1111 #
b1111 &
1%
1'
1"
#82
0"
#83
0%
0'
1"
#84
0"
#85
b1111 $
b0 !
b0 #
b0 &
1%
1'
1"
#86
0"
#87
0%
0'
1"
#88
0"
#89
b0 $
b1111 !
b1111 #
b1111 &
1%
1'
1"
#90
0"
#91
0%
0'
1"
#92
0"
#93
b1111 $
b0 !
b0 #
b0 &
1%
1'
1"
#94
0"
#95
0%
0'
1"
#96
0"
#97
b0 $
b1111 !
b1111 #
b1111 &
1%
1'
1"
#98
0"
#99
0%
0'
1"
